<?xml version="1.0" encoding="UTF-8" standalone="yes"?><ContractAwardNotice xmlns:ext="urn:oasis:names:specification:ubl:schema:xsd:CommonExtensionComponents-2" xmlns="urn:oasis:names:specification:ubl:schema:xsd:ContractAwardNotice-2" xmlns:ns8="urn:oasis:names:specification:ubl:schema:xsd:ContractNotice-2" xmlns:cac="urn:oasis:names:specification:ubl:schema:xsd:CommonAggregateComponents-2" xmlns:cbc="urn:oasis:names:specification:ubl:schema:xsd:CommonBasicComponents-2" xmlns:ns9="urn:oasis:names:specification:ubl:schema:xsd:PriorInformationNotice-2" xmlns:efac="http://data.europa.eu/p27/eforms-ubl-extension-aggregate-components/1" xmlns:efbc="http://data.europa.eu/p27/eforms-ubl-extension-basic-components/1" xmlns:efext="http://data.europa.eu/p27/eforms-ubl-extensions/1"><ext:UBLExtensions><ext:UBLExtension><ext:ExtensionContent><efext:EformsExtension><efbc:TransmissionDate>2025-06-06+02:00</efbc:TransmissionDate><efbc:TransmissionTime>00:00:00+02:00</efbc:TransmissionTime><efac:NoticeResult><efac:LotResult><cbc:ID schemeName="result">RES-0001</cbc:ID><cbc:TenderResultCode listName="winner-selection-status">selec-w</cbc:TenderResultCode><efac:LotTender><cbc:ID schemeName="tender">TEN-0001</cbc:ID></efac:LotTender><efac:ReceivedSubmissionsStatistics><efbc:StatisticsCode listName="received-submission-type">tenders</efbc:StatisticsCode><efbc:StatisticsNumeric>2</efbc:StatisticsNumeric></efac:ReceivedSubmissionsStatistics><efac:SettledContract><cbc:ID schemeName="contract">CON-0001</cbc:ID></efac:SettledContract><efac:TenderLot><cbc:ID schemeName="Lot">LOT-0001</cbc:ID></efac:TenderLot></efac:LotResult><efac:LotTender><cbc:ID schemeName="tender">TEN-0001</cbc:ID><cac:LegalMonetaryTotal><cbc:PayableAmount currencyID="EUR">139000</cbc:PayableAmount></cac:LegalMonetaryTotal><efac:TenderingParty><cbc:ID schemeName="tendering-party">TPA-0001</cbc:ID></efac:TenderingParty><efac:TenderLot><cbc:ID schemeName="Lot">LOT-0001</cbc:ID></efac:TenderLot><efac:TenderReference><cbc:ID>ETABLISSEMENTS LIEGEOIS-LOT-0001</cbc:ID></efac:TenderReference></efac:LotTender><efac:SettledContract><cbc:ID schemeName="contract">CON-0001</cbc:ID><cbc:IssueDate>2025-05-08+02:00</cbc:IssueDate><efac:ContractReference><cbc:ID>Etablissements Liegeois - LOT - 0001</cbc:ID></efac:ContractReference><efac:LotTender><cbc:ID schemeName="tender">TEN-0001</cbc:ID></efac:LotTender></efac:SettledContract><efac:TenderingParty><cbc:ID schemeName="tendering-party">TPA-0001</cbc:ID><cbc:Name>Etablissements Liegeois</cbc:Name><efac:Tenderer><cbc:ID schemeName="organization">ORG-0003</cbc:ID></efac:Tenderer></efac:TenderingParty></efac:NoticeResult><efac:NoticeSubType><cbc:SubTypeCode listName="notice-subtype">E4</cbc:SubTypeCode></efac:NoticeSubType><efac:Organizations><efac:Organization><efac:Company><cbc:WebsiteURI>http://cdsca-ocasc.be/</cbc:WebsiteURI><cac:PartyIdentification><cbc:ID schemeName="organization">ORG-0001</cbc:ID></cac:PartyIdentification><cac:PartyName><cbc:Name languageID="FRA">Office Central d'Action Sociale et Culturelle du Ministère de la Défense</cbc:Name></cac:PartyName><cac:PartyName><cbc:Name languageID="NLD">Centrale Dienst voor Sociale en Culturele Actie van het Ministerie van Landsverdediging</cbc:Name></cac:PartyName><cac:PostalAddress><cbc:StreetName>Kwartier Koningin Astrid Blok F Bruynstraat, 1</cbc:StreetName><cbc:CityName>Neder-Over-Heembeek</cbc:CityName><cbc:PostalZone>1120</cbc:PostalZone><cbc:CountrySubentityCode listName="nuts">BE100</cbc:CountrySubentityCode><cac:Country><cbc:IdentificationCode listName="country">BEL</cbc:IdentificationCode></cac:Country></cac:PostalAddress><cac:PartyLegalEntity><cbc:CompanyID>0222961725_3</cbc:CompanyID></cac:PartyLegalEntity><cac:Contact><cbc:Telephone>+32 4432583</cbc:Telephone><cbc:ElectronicMail>overheidsopdrachten@cdsca.be</cbc:ElectronicMail></cac:Contact></efac:Company></efac:Organization><efac:Organization><efac:Company><cbc:WebsiteURI>https://bosa.belgium.be</cbc:WebsiteURI><cac:PartyIdentification><cbc:ID schemeName="organization">ORG-0002</cbc:ID></cac:PartyIdentification><cac:PartyName><cbc:Name languageID="FRA">SPF Stratégie et Appui</cbc:Name></cac:PartyName><cac:PartyName><cbc:Name languageID="NLD">FOD Beleid en Ondersteuning</cbc:Name></cac:PartyName><cac:PostalAddress><cbc:StreetName>Simon Bolivarlaan 30, bus 1</cbc:StreetName><cbc:CityName>Brussel</cbc:CityName><cbc:PostalZone>1000</cbc:PostalZone><cbc:CountrySubentityCode listName="nuts">BE100</cbc:CountrySubentityCode><cac:Country><cbc:IdentificationCode listName="country">BEL</cbc:IdentificationCode></cac:Country></cac:PostalAddress><cac:PartyLegalEntity><cbc:CompanyID>BE001</cbc:CompanyID></cac:PartyLegalEntity><cac:Contact><cbc:Telephone>+32 2 740 80 00</cbc:Telephone><cbc:ElectronicMail>revise@publicprocurement.be</cbc:ElectronicMail></cac:Contact></efac:Company></efac:Organization><efac:Organization><efac:Company><cac:PartyIdentification><cbc:ID schemeName="organization">ORG-0003</cbc:ID></cac:PartyIdentification><cac:PartyName><cbc:Name languageID="FRA">ETABLISSEMENTS LIEGEOIS</cbc:Name></cac:PartyName><cac:PartyName><cbc:Name languageID="NLD">ETABLISSEMENTS LIEGEOIS</cbc:Name></cac:PartyName><cac:PostalAddress><cbc:StreetName>Avenue de la Rousselière 67</cbc:StreetName><cbc:CityName>Liège</cbc:CityName><cbc:PostalZone>4020</cbc:PostalZone><cbc:CountrySubentityCode listName="nuts">BE332</cbc:CountrySubentityCode><cac:Country><cbc:IdentificationCode listName="country">BEL</cbc:IdentificationCode></cac:Country></cac:PostalAddress><cac:PartyLegalEntity><cbc:CompanyID>1002879337_df98c03a-f86e-4e00-9f1e-113a7753e6c9</cbc:CompanyID></cac:PartyLegalEntity><cac:Contact><cbc:Telephone>0465512634</cbc:Telephone><cbc:ElectronicMail>etablissements.liegeois@gmail.com</cbc:ElectronicMail></cac:Contact></efac:Company></efac:Organization><efac:Organization><efac:Company><cac:PartyIdentification><cbc:ID schemeName="organization">ORG-0004</cbc:ID></cac:PartyIdentification><cac:PartyName><cbc:Name languageID="NLD">Raad van State</cbc:Name></cac:PartyName><cac:PartyName><cbc:Name languageID="FRA">Conseil d'Etat</cbc:Name></cac:PartyName><cac:PostalAddress><cbc:CityName>Bruxelles</cbc:CityName><cbc:CountrySubentityCode listName="nuts">BE100</cbc:CountrySubentityCode><cac:Country><cbc:IdentificationCode listName="country">BEL</cbc:IdentificationCode></cac:Country></cac:PostalAddress><cac:PartyLegalEntity><cbc:CompanyID>0931.814.266</cbc:CompanyID></cac:PartyLegalEntity></efac:Company></efac:Organization></efac:Organizations></efext:EformsExtension></ext:ExtensionContent></ext:UBLExtension></ext:UBLExtensions><cbc:UBLVersionID>2.3</cbc:UBLVersionID><cbc:CustomizationID>eforms-sdk-1.13</cbc:CustomizationID><cbc:ID schemeName="notice-id">62887adb-e6cb-4b36-b5af-2c4b7a5d37fe</cbc:ID><cbc:ContractFolderID>c76f67ee-7a91-4109-a006-3d8c51651508</cbc:ContractFolderID><cbc:IssueDate>2025-06-06+02:00</cbc:IssueDate><cbc:IssueTime>00:00:00+02:00</cbc:IssueTime><cbc:VersionID>01</cbc:VersionID><cbc:RegulatoryDomain>32014L0024</cbc:RegulatoryDomain><cbc:NoticeTypeCode listName="result">can-standard</cbc:NoticeTypeCode><cbc:NoticeLanguageCode listName="language">NLD</cbc:NoticeLanguageCode><cac:AdditionalNoticeLanguage><cbc:ID>FRA</cbc:ID></cac:AdditionalNoticeLanguage><cac:ContractingParty><cbc:BuyerProfileURI>https://www.publicprocurement.be/bda?organisationIds=3&amp;includeOrganisationChildren=true</cbc:BuyerProfileURI><cac:ContractingPartyType><cbc:PartyTypeCode listName="buyer-legal-type">body-pl</cbc:PartyTypeCode></cac:ContractingPartyType><cac:ContractingPartyType><cbc:PartyTypeCode listName="buyer-contracting-type">not-cont-ent</cbc:PartyTypeCode></cac:ContractingPartyType><cac:ContractingActivity><cbc:ActivityTypeCode listName="authority-activity">hc-am</cbc:ActivityTypeCode></cac:ContractingActivity><cac:Party><cac:PartyIdentification><cbc:ID schemeName="organization">ORG-0001</cbc:ID></cac:PartyIdentification><cac:ServiceProviderParty><cbc:ServiceTypeCode listName="organisation-role">ted-esen</cbc:ServiceTypeCode><cac:Party><cac:PartyIdentification><cbc:ID schemeName="organization">ORG-0002</cbc:ID></cac:PartyIdentification></cac:Party></cac:ServiceProviderParty></cac:Party></cac:ContractingParty><cac:TenderingProcess><cbc:Description languageID="FRA">Pour ce marché, les réglementations nationales de la procédure suivante seront appliquées : procédure négociée directe avec publication préalable</cbc:Description><cbc:Description languageID="NLD">Voor deze opdracht wordt de nationale regelgeving van volgende procedure toegepast: vereenvoudigde onderhandelingsprocedure met voorafgaande bekendmaking</cbc:Description><cbc:ProcedureCode listName="procurement-procedure-type">oth-single</cbc:ProcedureCode></cac:TenderingProcess><cac:ProcurementProject><cbc:ID schemeName="InternalID">21007</cbc:ID><cbc:Name languageID="NLD">De reparatie en aanpassing van de elektrische installaties in de woningen van de Centrale Dienst voor sociale en culturele actie van het Ministerie van Landsverdediging in Spa, Saive, Visé, Rocourt, Amay, Ampsin, Boirs, Glons, Slins, Eupen, Stembert en Elsenborn.</cbc:Name><cbc:Name languageID="FRA">Travaux de dépannage et mise en conformité des installations électriques dans des logements de l’Office Central D’Action Sociale et Culturelle du Ministère de la Défense situés à Spa, Saive, Visé, Rocourt, Amay, Ampsin, Boirs, Glons, Slins, Eupen, Stembert et Elsenborn.</cbc:Name><cbc:Description languageID="NLD">Dit contract betreft de herstelling en conform maken van de elektrische installaties in de woningen van de Centrale Dienst voor sociale en culturele actie van het Ministerie van Landsverdediging (hierna CDSCA) in Spa (114 woningen) Saive (109 woningen), Visé (4 woningen), Rocourt (92 woningen), Amay (24 woningen), Ampsin (20 woningen), Boirs (1 woning), Slins (26 woningen), Glons (10 woningen), Eupen (6 woningen), Stembert (8 woningen) en Elsenborn (54 woningen). Het gaat om een contract van 1 jaar met de mogelijkheid om het contract jaarlijks stilzwijgend te verlengen onder exact dezelfde voorwaarden en maximaal 3 keer (zie punt 2.5 van de CSC). verlengen onder exact dezelfde voorwaarden en maximaal 3 keer (zie punt 2.5 van de CSC). De maximaal mogelijke waarde van het contract is €139.000. Het contract wordt automatisch beëindigd wanneer dit bedrag is bereikt of na 4 jaar.</cbc:Description><cbc:Description languageID="FRA">Le présent marché porte sur les travaux de dépannage et mise en conformité des installations électriques dans des logements de l’Office Central d’Action Sociale et Culturelle du Ministère De La Défense (ci-après OCASC) à Spa (114 logements), Saive ( 109 logements), Visé ( 4 logements), Rocourt (92 logements), Amay (24 logements), Ampsin ( 20 logements), Boirs ( 1 logement), Slins (26 Logements) ,Glons ( 10 logements), Eupen ( 6 logements), Stembert ( 8 logements) et Elsenborn ( 54 logements). Il s’agit d’un contrat de 1 an avec la possibilité annuelle de prolonger le contrat d’une manière tacite sous exactement les mêmes conditions et au maximum 3 fois (voir point 2.5 du CSC). La valeur maximale possible du marché est de 139.000 €. Le marché prend fin de plein droit ce qui arrive d’abord, soit au moment où ce montant serait atteint soit après 4 ans.</cbc:Description><cbc:ProcurementTypeCode listName="contract-nature">works</cbc:ProcurementTypeCode><cac:MainCommodityClassification><cbc:ItemClassificationCode listName="cpv">45310000</cbc:ItemClassificationCode></cac:MainCommodityClassification><cac:AdditionalCommodityClassification><cbc:ItemClassificationCode listName="cpv">50711000</cbc:ItemClassificationCode></cac:AdditionalCommodityClassification><cac:RealizedLocation><cac:Address><cbc:CountrySubentityCode listName="nuts">BE335</cbc:CountrySubentityCode><cac:Country><cbc:IdentificationCode listName="country">BEL</cbc:IdentificationCode></cac:Country></cac:Address></cac:RealizedLocation><cac:RealizedLocation><cac:Address><cbc:CountrySubentityCode listName="nuts">BE332</cbc:CountrySubentityCode><cac:Country><cbc:IdentificationCode listName="country">BEL</cbc:IdentificationCode></cac:Country></cac:Address></cac:RealizedLocation><cac:RealizedLocation><cac:Address><cbc:CountrySubentityCode listName="nuts">BE331</cbc:CountrySubentityCode><cac:Country><cbc:IdentificationCode listName="country">BEL</cbc:IdentificationCode></cac:Country></cac:Address></cac:RealizedLocation><cac:RealizedLocation><cac:Address><cbc:CountrySubentityCode listName="nuts">BE336</cbc:CountrySubentityCode><cac:Country><cbc:IdentificationCode listName="country">BEL</cbc:IdentificationCode></cac:Country></cac:Address></cac:RealizedLocation></cac:ProcurementProject><cac:ProcurementProjectLot><cbc:ID schemeName="Lot">LOT-0001</cbc:ID><cac:TenderingTerms><ext:UBLExtensions><ext:UBLExtension><ext:ExtensionContent><efext:EformsExtension><efac:StrategicProcurement><efbc:ApplicableLegalBasis listName="cvd-scope">false</efbc:ApplicableLegalBasis></efac:StrategicProcurement></efext:EformsExtension></ext:ExtensionContent></ext:UBLExtension></ext:UBLExtensions><cac:AppealTerms><cac:AppealReceiverParty><cac:PartyIdentification><cbc:ID schemeName="organization">ORG-0004</cbc:ID></cac:PartyIdentification></cac:AppealReceiverParty></cac:AppealTerms></cac:TenderingTerms><cac:TenderingProcess><cac:FrameworkAgreement><cac:SubsequentProcessTenderRequirement><cbc:Name>buyer-categories</cbc:Name></cac:SubsequentProcessTenderRequirement></cac:FrameworkAgreement><cac:ContractingSystem><cbc:ContractingSystemTypeCode listName="framework-agreement">none</cbc:ContractingSystemTypeCode></cac:ContractingSystem><cac:ContractingSystem><cbc:ContractingSystemTypeCode listName="dps-usage">none</cbc:ContractingSystemTypeCode></cac:ContractingSystem></cac:TenderingProcess><cac:ProcurementProject><cbc:ID schemeName="InternalID">1</cbc:ID><cbc:Name languageID="FRA">21007 - Travaux de dépannage et mise en conformité des installations électriques dans des logements de l’Office Central D’Action Sociale et Culturelle du Ministère de la Défense situés à Spa, Saive, Visé, Rocourt, Amay, Ampsin, Boirs, Glons, Slins, Eupen, Stembert et Elsenborn.</cbc:Name><cbc:Name languageID="NLD">21007 - De reparatie en aanpassing van de elektrische installaties in de woningen van de Centrale Dienst voor sociale en culturele actie van het Ministerie van Landsverdediging in Spa, Saive, Visé, Rocourt, Amay, Ampsin, Boirs, Glons, Slins, Eupen, Stembert en Elsenborn.</cbc:Name><cbc:Description languageID="FRA">Le présent marché porte sur les travaux de dépannage et mise en conformité des installations électriques dans des logements de l’Office Central d’Action Sociale et Culturelle du Ministère De La Défense (ci-après OCASC) à Spa (114 logements), Saive ( 109 logements), Visé ( 4 logements), Rocourt (92 logements), Amay (24 logements), Ampsin ( 20 logements), Boirs ( 1 logement), Slins (26 Logements) ,Glons ( 10 logements), Eupen ( 6 logements), Stembert ( 8 logements) et Elsenborn ( 54 logements). Il s’agit d’un contrat de 1 an avec la possibilité annuelle de prolonger le contrat d’une manière tacite sous exactement les mêmes conditions et au maximum 3 fois (voir point 2.5 du CSC). La valeur maximale possible du marché est de 139.000 €. Le marché prend fin de plein droit ce qui arrive d’abord, soit au moment où ce montant serait atteint soit après 4 ans.</cbc:Description><cbc:Description languageID="NLD">Dit contract betreft de herstelling en conform maken van de elektrische installaties in de woningen van de Centrale Dienst voor sociale en culturele actie van het Ministerie van Landsverdediging (hierna CDSCA) in Spa (114 woningen) Saive (109 woningen), Visé (4 woningen), Rocourt (92 woningen), Amay (24 woningen), Ampsin (20 woningen), Boirs (1 woning), Slins (26 woningen), Glons (10 woningen), Eupen (6 woningen), Stembert (8 woningen) en Elsenborn (54 woningen). Het gaat om een contract van 1 jaar met de mogelijkheid om het contract jaarlijks stilzwijgend te verlengen onder exact dezelfde voorwaarden en maximaal 3 keer (zie punt 2.5 van de CSC). verlengen onder exact dezelfde voorwaarden en maximaal 3 keer (zie punt 2.5 van de CSC). De maximaal mogelijke waarde van het contract is €139.000. Het contract wordt automatisch beëindigd wanneer dit bedrag is bereikt of na 4 jaar. </cbc:Description><cbc:ProcurementTypeCode listName="contract-nature">works</cbc:ProcurementTypeCode><cac:MainCommodityClassification><cbc:ItemClassificationCode listName="cpv">45310000</cbc:ItemClassificationCode></cac:MainCommodityClassification><cac:AdditionalCommodityClassification><cbc:ItemClassificationCode listName="cpv">50711000</cbc:ItemClassificationCode></cac:AdditionalCommodityClassification><cac:RealizedLocation><cac:Address><cbc:CountrySubentityCode listName="nuts">BE335</cbc:CountrySubentityCode><cac:Country><cbc:IdentificationCode listName="country">BEL</cbc:IdentificationCode></cac:Country></cac:Address></cac:RealizedLocation><cac:RealizedLocation><cac:Address><cbc:CountrySubentityCode listName="nuts">BE332</cbc:CountrySubentityCode><cac:Country><cbc:IdentificationCode listName="country">BEL</cbc:IdentificationCode></cac:Country></cac:Address></cac:RealizedLocation><cac:RealizedLocation><cac:Address><cbc:CountrySubentityCode listName="nuts">BE331</cbc:CountrySubentityCode><cac:Country><cbc:IdentificationCode listName="country">BEL</cbc:IdentificationCode></cac:Country></cac:Address></cac:RealizedLocation><cac:RealizedLocation><cac:Address><cbc:CountrySubentityCode listName="nuts">BE336</cbc:CountrySubentityCode><cac:Country><cbc:IdentificationCode listName="country">BEL</cbc:IdentificationCode></cac:Country></cac:Address></cac:RealizedLocation><cac:PlannedPeriod><cbc:StartDate>2025-05-10+02:00</cbc:StartDate><cbc:EndDate>2026-05-01+02:00</cbc:EndDate></cac:PlannedPeriod><cac:ContractExtension><cbc:MaximumNumberNumeric>3</cbc:MaximumNumberNumeric></cac:ContractExtension></cac:ProcurementProject></cac:ProcurementProjectLot><cac:TenderResult><cbc:AwardDate>2000-01-01+01:00</cbc:AwardDate></cac:TenderResult></ContractAwardNotice>