<?xml version="1.0" encoding="UTF-8" standalone="yes"?><ContractNotice xmlns:ext="urn:oasis:names:specification:ubl:schema:xsd:CommonExtensionComponents-2" xmlns="urn:oasis:names:specification:ubl:schema:xsd:ContractNotice-2" xmlns:ns7="urn:oasis:names:specification:ubl:schema:xsd:ContractAwardNotice-2" xmlns:cac="urn:oasis:names:specification:ubl:schema:xsd:CommonAggregateComponents-2" xmlns:cbc="urn:oasis:names:specification:ubl:schema:xsd:CommonBasicComponents-2" xmlns:ns9="urn:oasis:names:specification:ubl:schema:xsd:PriorInformationNotice-2" xmlns:efac="http://data.europa.eu/p27/eforms-ubl-extension-aggregate-components/1" xmlns:efbc="http://data.europa.eu/p27/eforms-ubl-extension-basic-components/1" xmlns:efext="http://data.europa.eu/p27/eforms-ubl-extensions/1"><ext:UBLExtensions><ext:UBLExtension><ext:ExtensionContent><efext:EformsExtension><efbc:TransmissionDate>2025-06-06+02:00</efbc:TransmissionDate><efbc:TransmissionTime>00:00:00+02:00</efbc:TransmissionTime><efac:NoticeSubType><cbc:SubTypeCode listName="notice-subtype">16</cbc:SubTypeCode></efac:NoticeSubType><efac:Organizations><efac:Organization><efac:Company><cbc:WebsiteURI>http://www.aptaskil.be/</cbc:WebsiteURI><cac:PartyIdentification><cbc:ID schemeName="organization">ORG-0001</cbc:ID></cac:PartyIdentification><cac:PartyName><cbc:Name languageID="FRA">aptaskil asbl</cbc:Name></cac:PartyName><cac:PostalAddress><cbc:StreetName>Zoning Industriel de Seneffe - Zone C</cbc:StreetName><cbc:CityName>Seneffe</cbc:CityName><cbc:PostalZone>7180</cbc:PostalZone><cbc:CountrySubentityCode listName="nuts">BE32C</cbc:CountrySubentityCode><cac:Country><cbc:IdentificationCode listName="country">BEL</cbc:IdentificationCode></cac:Country></cac:PostalAddress><cac:PartyLegalEntity><cbc:CompanyID>0476.430.049</cbc:CompanyID></cac:PartyLegalEntity><cac:Contact><cbc:Name>Isabelle Legentil</cbc:Name><cbc:JobTitle>Directrice Générale</cbc:JobTitle><cbc:Telephone>+32 64310700</cbc:Telephone><cbc:Telefax>+32 64260297</cbc:Telefax><cbc:ElectronicMail>i.legentil@aptaskil.be</cbc:ElectronicMail></cac:Contact></efac:Company></efac:Organization><efac:Organization><efac:Company><cac:PartyIdentification><cbc:ID schemeName="organization">ORG-0002</cbc:ID></cac:PartyIdentification><cac:PartyName><cbc:Name languageID="FRA">Tribunal de Première Instance de l'Arrondissement judiciaire de Charleroi</cbc:Name></cac:PartyName><cac:PostalAddress><cbc:StreetName>Av. du Général Michel 2/1</cbc:StreetName><cbc:CityName>Charleroi</cbc:CityName><cbc:PostalZone>6000</cbc:PostalZone><cbc:CountrySubentityCode listName="nuts">BE32B</cbc:CountrySubentityCode><cac:Country><cbc:IdentificationCode listName="country">BEL</cbc:IdentificationCode></cac:Country></cac:PostalAddress><cac:PartyLegalEntity><cbc:CompanyID>BE 0308.357.753</cbc:CompanyID></cac:PartyLegalEntity><cac:Contact><cbc:Telephone>+32 71236511</cbc:Telephone><cbc:ElectronicMail>conclusions.tpi.civil.charleroi@just.fgov.be</cbc:ElectronicMail></cac:Contact></efac:Company></efac:Organization><efac:Organization><efac:Company><cac:PartyIdentification><cbc:ID schemeName="organization">ORG-0003</cbc:ID></cac:PartyIdentification><cac:PartyName><cbc:Name languageID="FRA">3P - Aanbieder van diensten / Prestataire de services</cbc:Name></cac:PartyName><cac:PostalAddress><cbc:CityName>Antwerpen / Anvers</cbc:CityName><cbc:PostalZone>2000</cbc:PostalZone><cbc:CountrySubentityCode listName="nuts">BE211</cbc:CountrySubentityCode><cac:Country><cbc:IdentificationCode listName="country">BEL</cbc:IdentificationCode></cac:Country></cac:PostalAddress><cac:PartyLegalEntity><cbc:CompanyID>BE 0475.480.736</cbc:CompanyID></cac:PartyLegalEntity><cac:Contact><cbc:Telephone>+32 3 294 30 51</cbc:Telephone><cbc:ElectronicMail>info@3p.eu</cbc:ElectronicMail></cac:Contact></efac:Company></efac:Organization></efac:Organizations></efext:EformsExtension></ext:ExtensionContent></ext:UBLExtension></ext:UBLExtensions><cbc:UBLVersionID>2.3</cbc:UBLVersionID><cbc:CustomizationID>eforms-sdk-1.13</cbc:CustomizationID><cbc:ID schemeName="notice-id">794e804c-a0da-46d1-9100-c5d85deba837</cbc:ID><cbc:ContractFolderID>65e65e0d-dddc-4954-a72b-b2cd52aefbd0</cbc:ContractFolderID><cbc:IssueDate>2025-06-06+02:00</cbc:IssueDate><cbc:IssueTime>00:00:00+02:00</cbc:IssueTime><cbc:VersionID>01</cbc:VersionID><cbc:RegulatoryDomain>32014L0024</cbc:RegulatoryDomain><cbc:NoticeTypeCode listName="competition">cn-standard</cbc:NoticeTypeCode><cbc:NoticeLanguageCode listName="language">FRA</cbc:NoticeLanguageCode><cac:ContractingParty><cac:ContractingPartyType><cbc:PartyTypeCode listName="buyer-legal-type">body-pl</cbc:PartyTypeCode></cac:ContractingPartyType><cac:ContractingActivity><cbc:ActivityTypeCode listName="authority-activity">gen-pub</cbc:ActivityTypeCode></cac:ContractingActivity><cac:Party><cac:PartyIdentification><cbc:ID schemeName="organization">ORG-0001</cbc:ID></cac:PartyIdentification><cac:ServiceProviderParty><cbc:ServiceTypeCode listName="organization-role">serv-prov</cbc:ServiceTypeCode><cac:Party><cac:PartyIdentification><cbc:ID schemeName="organization">ORG-0003</cbc:ID></cac:PartyIdentification></cac:Party></cac:ServiceProviderParty></cac:Party></cac:ContractingParty><cac:TenderingTerms><cac:TendererQualificationRequest><cac:SpecificTendererRequirement><cbc:TendererRequirementTypeCode listName="exclusion-grounds-source">epo-procurement-document</cbc:TendererRequirementTypeCode></cac:SpecificTendererRequirement></cac:TendererQualificationRequest></cac:TenderingTerms><cac:TenderingProcess><cbc:ProcedureCode listName="procurement-procedure-type">open</cbc:ProcedureCode><cac:ProcessJustification><cbc:ProcessReasonCode listName="accelerated-procedure">false</cbc:ProcessReasonCode></cac:ProcessJustification></cac:TenderingProcess><cac:ProcurementProject><cbc:ID schemeName="InternalID">PPP0U5-232/5085/IL/CG/PNRR/2024/011</cbc:ID><cbc:Name languageID="FRA">MARCHÉ DE FOURNITURES - ACHAT D'ÉQUIPEMENTS POUR UNE COMMUNICATION ET UNE SIGNALÉTIQUE DIGITALE (estampillé DNSH)</cbc:Name><cbc:Description languageID="FRA">aptaskil asbl est un centre de compétences qui forme aux métiers de la chimie, de la biopharmacie et des biotechnologies. Nous formons 3 types de publics : des personnes travaillant dans les entreprises chimiques et pharmaceutiques, des enseignants et des étudiants, des chercheurs d’emploi. 

Pour répondre à la forte croissance du secteur, nous agrandissons notre centre et disposons de nouvelles salles de cours, et de nouvelles zones d’apprentissage pratique réparties sur deux sites, à Seneffe (4.000 m2) et à Liège (800 m2). Nous souhaitons équiper ces lieux d’un dispositif de communication et de signalétique digitale.

Principe DNSH : Cet investissement est subventionné par l’Europe et la Région wallonne (Plan National de Relance et de Résilience et Plan de Relance de la Wallonie). Il en découle que le présent marché public intègre le respect du principe DNSH et les résultats de l’analyse ex hante spécifiques aux équipements numériques notifiés dans l’accord de subvention. Dans ce cadre, des clauses contractuelles, des exigences techniques et des critères d’attribution spécifiques au principe DNSH ont été intégrées au présent marché. Des informations complémentaires pour aider à la compréhension du principe DNSH sont intégrées au point I.14 Financement/principes DNSH

Objet social du marché : du fait de son activité de dispense de formations, le Centre de compétence aptaskil assure une mission sociale en participant à l’insertion professionnelle des futurs travailleurs (chercheurs d’emploi et des étudiants) et au maintien de l’employabilité des travailleurs en activité. Le présent marché permettra de soutenir cette mission sociale en permettant aux apprenants d’évoluer dans un environnement digital. Le soumissionnaire, par son activité de livraison et d’installation d’équipements, participera donc au renforcement de la mission sociale d’aptaskil.   </cbc:Description><cbc:ProcurementTypeCode listName="contract-nature">supplies</cbc:ProcurementTypeCode><cac:MainCommodityClassification><cbc:ItemClassificationCode listName="cpv">30121430</cbc:ItemClassificationCode></cac:MainCommodityClassification><cac:RealizedLocation><cac:Address><cbc:CountrySubentityCode listName="nuts">BE32B</cbc:CountrySubentityCode><cac:Country><cbc:IdentificationCode listName="country">BEL</cbc:IdentificationCode></cac:Country></cac:Address></cac:RealizedLocation><cac:RealizedLocation><cac:Address><cbc:CountrySubentityCode listName="nuts">BE331</cbc:CountrySubentityCode><cac:Country><cbc:IdentificationCode listName="country">BEL</cbc:IdentificationCode></cac:Country></cac:Address></cac:RealizedLocation><cac:RealizedLocation><cac:Address><cbc:CountrySubentityCode listName="nuts">BE332</cbc:CountrySubentityCode><cac:Country><cbc:IdentificationCode listName="country">BEL</cbc:IdentificationCode></cac:Country></cac:Address></cac:RealizedLocation><cac:RealizedLocation><cac:Address><cbc:CountrySubentityCode listName="nuts">BE335</cbc:CountrySubentityCode><cac:Country><cbc:IdentificationCode listName="country">BEL</cbc:IdentificationCode></cac:Country></cac:Address></cac:RealizedLocation><cac:RealizedLocation><cac:Address><cbc:CountrySubentityCode listName="nuts">BE334</cbc:CountrySubentityCode><cac:Country><cbc:IdentificationCode listName="country">BEL</cbc:IdentificationCode></cac:Country></cac:Address></cac:RealizedLocation><cac:RealizedLocation><cac:Address><cbc:CountrySubentityCode listName="nuts">BE336</cbc:CountrySubentityCode><cac:Country><cbc:IdentificationCode listName="country">BEL</cbc:IdentificationCode></cac:Country></cac:Address></cac:RealizedLocation><cac:RealizedLocation><cac:Address><cbc:CountrySubentityCode listName="nuts">BE32B</cbc:CountrySubentityCode><cac:Country><cbc:IdentificationCode listName="country">BEL</cbc:IdentificationCode></cac:Country></cac:Address></cac:RealizedLocation><cac:RealizedLocation><cac:Address><cbc:CountrySubentityCode listName="nuts">BE331</cbc:CountrySubentityCode><cac:Country><cbc:IdentificationCode listName="country">BEL</cbc:IdentificationCode></cac:Country></cac:Address></cac:RealizedLocation><cac:RealizedLocation><cac:Address><cbc:CountrySubentityCode listName="nuts">BE332</cbc:CountrySubentityCode><cac:Country><cbc:IdentificationCode listName="country">BEL</cbc:IdentificationCode></cac:Country></cac:Address></cac:RealizedLocation><cac:RealizedLocation><cac:Address><cbc:CountrySubentityCode listName="nuts">BE335</cbc:CountrySubentityCode><cac:Country><cbc:IdentificationCode listName="country">BEL</cbc:IdentificationCode></cac:Country></cac:Address></cac:RealizedLocation><cac:RealizedLocation><cac:Address><cbc:CountrySubentityCode listName="nuts">BE334</cbc:CountrySubentityCode><cac:Country><cbc:IdentificationCode listName="country">BEL</cbc:IdentificationCode></cac:Country></cac:Address></cac:RealizedLocation><cac:RealizedLocation><cac:Address><cbc:CountrySubentityCode listName="nuts">BE336</cbc:CountrySubentityCode><cac:Country><cbc:IdentificationCode listName="country">BEL</cbc:IdentificationCode></cac:Country></cac:Address></cac:RealizedLocation></cac:ProcurementProject><cac:ProcurementProjectLot><cbc:ID schemeName="Lot">LOT-0001</cbc:ID><cac:TenderingTerms><cbc:VariantConstraintCode listName="permission">not-allowed</cbc:VariantConstraintCode><cbc:FundingProgramCode listName="eu-funded">no-eu-funds</cbc:FundingProgramCode><cbc:RequiredCurriculaCode listName="requirement-stage">not-requ</cbc:RequiredCurriculaCode><cac:RequiredFinancialGuarantee><cbc:GuaranteeTypeCode listName="tender-guarantee-required">false</cbc:GuaranteeTypeCode></cac:RequiredFinancialGuarantee><cac:CallForTendersDocumentReference><cbc:ID>DOC 01</cbc:ID><cbc:DocumentType>non-restricted-document</cbc:DocumentType><cbc:LanguageID>FRA</cbc:LanguageID><cac:Attachment><cac:ExternalReference><cbc:URI>https://cloud.3p.eu/Downloads/1/232/U5/2024</cbc:URI></cac:ExternalReference></cac:Attachment></cac:CallForTendersDocumentReference><cac:TendererQualificationRequest><cac:SpecificTendererRequirement><cbc:TendererRequirementTypeCode listName="reserved-procurement">none</cbc:TendererRequirementTypeCode></cac:SpecificTendererRequirement></cac:TendererQualificationRequest><cac:TendererQualificationRequest><cbc:CompanyLegalFormCode listName="required">false</cbc:CompanyLegalFormCode></cac:TendererQualificationRequest><cac:TendererQualificationRequest><cac:SpecificTendererRequirement><cbc:TendererRequirementTypeCode listName="selection-criteria-source">epo-procurement-document</cbc:TendererRequirementTypeCode></cac:SpecificTendererRequirement></cac:TendererQualificationRequest><cac:ContractExecutionRequirement><cbc:ExecutionRequirementCode listName="ecatalog-submission">not-allowed</cbc:ExecutionRequirementCode></cac:ContractExecutionRequirement><cac:ContractExecutionRequirement><cbc:ExecutionRequirementCode listName="einvoicing">required</cbc:ExecutionRequirementCode></cac:ContractExecutionRequirement><cac:ContractExecutionRequirement><cbc:ExecutionRequirementCode listName="reserved-execution">no</cbc:ExecutionRequirementCode></cac:ContractExecutionRequirement><cac:ContractExecutionRequirement><cbc:ExecutionRequirementCode listName="esignature-submission">false</cbc:ExecutionRequirementCode></cac:ContractExecutionRequirement><cac:AwardingTerms><cac:AwardingCriterion><cac:SubordinateAwardingCriterion><ext:UBLExtensions><ext:UBLExtension><ext:ExtensionContent><efext:EformsExtension><efac:AwardCriterionParameter><efbc:ParameterCode listName="number-weight">poi-exa</efbc:ParameterCode><efbc:ParameterNumeric>65</efbc:ParameterNumeric></efac:AwardCriterionParameter></efext:EformsExtension></ext:ExtensionContent></ext:UBLExtension></ext:UBLExtensions><cbc:AwardingCriterionTypeCode listName="award-criterion-type">cost</cbc:AwardingCriterionTypeCode><cbc:Description languageID="FRA">Prix</cbc:Description><cbc:CalculationExpression languageID="FRA">Règle de trois; Score offre = (prix de l’offre la plus basse / prix de l’offre) * pondération du critère prix</cbc:CalculationExpression></cac:SubordinateAwardingCriterion><cac:SubordinateAwardingCriterion><ext:UBLExtensions><ext:UBLExtension><ext:ExtensionContent><efext:EformsExtension><efac:AwardCriterionParameter><efbc:ParameterCode listName="number-weight">poi-exa</efbc:ParameterCode><efbc:ParameterNumeric>5</efbc:ParameterNumeric></efac:AwardCriterionParameter></efext:EformsExtension></ext:ExtensionContent></ext:UBLExtension></ext:UBLExtensions><cbc:AwardingCriterionTypeCode listName="award-criterion-type">quality</cbc:AwardingCriterionTypeCode><cbc:Description languageID="FRA">Principe DNSH - Critère d'attribution CAG - Extension de la durée de la garantie du fabricant des écrans au delà de la durée minimum des écrans </cbc:Description><cbc:CalculationExpression languageID="FRA">Principe DNSH - Critère d’attribution CAG- Extension de la durée de garantie du fabricant des écrans au-delà de la durée minimum spécifiée pour les écrans au point III Description des exigences techniques / Spécifications relatives au principe DNSH / ST3)

La durée de garantie du fabricant exigée pour les écrans est de minimum 3 ans (cf. point III Description des exigences techniques / Spécifications relatives au principe DNSH / ST3). 

Une durée de garantie supérieure peut-être proposée par le soumissionnaire. Elle sera commune aux 4 types d’écrans et sera évaluée comme ci-après:
Durée de garantie égale à 4 ans: 2,5 points
Durée de garantie supérieure ou égale à 5 ans: 5,0 points


Vérification : Pour chaque modèle, le soumissionnaire fournit une preuve écrite de l’existence d’une garantie du fabriquant
</cbc:CalculationExpression></cac:SubordinateAwardingCriterion><cac:SubordinateAwardingCriterion><ext:UBLExtensions><ext:UBLExtension><ext:ExtensionContent><efext:EformsExtension><efac:AwardCriterionParameter><efbc:ParameterCode listName="number-weight">poi-exa</efbc:ParameterCode><efbc:ParameterNumeric>5</efbc:ParameterNumeric></efac:AwardCriterionParameter></efext:EformsExtension></ext:ExtensionContent></ext:UBLExtension></ext:UBLExtensions><cbc:AwardingCriterionTypeCode listName="award-criterion-type">quality</cbc:AwardingCriterionTypeCode><cbc:Description languageID="FRA">Principe DNSH - Critère d'attribution CA6 - Amélioration dénergie au delà du seuil spécifié pour les écrans</cbc:Description><cbc:CalculationExpression languageID="FRA">Principe DNSH – Critère d’Attribution CA6 - Amélioration de la consommation d’énergie au-delà du seuil spécifié pour les écrans (cf. point III Description des exigences techniques / Spécifications principe DNSH/ST19)

Des points seront attribués si l’ensemble des écrans appartiennent à une et une seule classe énergétique supérieure à D (les 4 types d’écrans doivent appartenir à une même classe)

Classe d’efficacité énergétique	Indice d’efficacité énergétique	Points
A	IEE &lt; 0,30	5,00 points
B	0,30 ≤ IEE &lt; 0,40	3,30 points
C	0,40 ≤ IEE &lt; 0,50	1,15 points
Si les écrans présentés sont de classes énergétiques différentes, aucun point n’est attribué.

Vérification: Pour chaque modèle, le soumissionnaire doit fournir l’étiquette énergétique en cours de validité délivrée conformément au règlement-cadre de l’UE sur l’étiquetage énergétique (2017/1369) 
</cbc:CalculationExpression></cac:SubordinateAwardingCriterion><cac:SubordinateAwardingCriterion><ext:UBLExtensions><ext:UBLExtension><ext:ExtensionContent><efext:EformsExtension><efac:AwardCriterionParameter><efbc:ParameterCode listName="number-weight">poi-exa</efbc:ParameterCode><efbc:ParameterNumeric>5</efbc:ParameterNumeric></efac:AwardCriterionParameter></efext:EformsExtension></ext:ExtensionContent></ext:UBLExtension></ext:UBLExtensions><cbc:AwardingCriterionTypeCode listName="award-criterion-type">quality</cbc:AwardingCriterionTypeCode><cbc:Description languageID="FRA">Principe DNSH - Critère d'attribution CA7 - Restriction applicables aux substances extrémement préocuupante (SVHC) dans les écrans</cbc:Description><cbc:CalculationExpression languageID="FRA">Principe DNSH – Critère d’Attribution CA7 – Restriction applicables aux substances extrêmement préoccupante (SVHC) dans les écrans

5 points seront attribués quand aucune substances figurant sur la liste des substances identifiées du règlement REACH n’est intentionnellement ajoutée à plus de 0,1% (masse/masse), pour les 4 types d’écrans, dans chacun des sous-ensembles suivants:
•	Cartes mères avec unité centrale, RAM, processeurs graphiques préinstallés ;
•	Dispositif d’affichage (rétroéclairage inclus)
•	Boitiers et cadres
•	Clavier externe, souris et/ou pavé tactile ;
•	Câbles électriques externes pour courant continu et courant alternatif (y compris adaptateurs et blocs d’alimentation)
Il convient de garantir la conformité avec la dernière version de la liste de substances identifiées du règlement REACH disponible au moment de l’appel d’offre (*)

Vérification: le soumissionnaire fournira une déclaration de conformité pour ce critère. Des documents fondés sur la norme CEI 62474 ou une norme équivalente (par exemple documents élaborés conformément au système de contrôle des substances, tels que les analyses et évaluations de la conformité des fournisseurs) peuvent être utilisés.

Les produits porteurs d’un label écologique de type I pertinent (selon la norme ISO14024) satisfaisant aux exigences spécifiées seront réputés conformes 

(*) La liste des substances extrêmement préoccupantes identifiées en vue de leur autorisation est publié conformément à l’article 59, paragraphe 10, du règlement REACH et est périodiquement mise à jour sur le site de l’ECHA (https://echa.europa.eu/fr/candidate-list-table )
</cbc:CalculationExpression></cac:SubordinateAwardingCriterion><cac:SubordinateAwardingCriterion><ext:UBLExtensions><ext:UBLExtension><ext:ExtensionContent><efext:EformsExtension><efac:AwardCriterionParameter><efbc:ParameterCode listName="number-weight">poi-exa</efbc:ParameterCode><efbc:ParameterNumeric>5</efbc:ParameterNumeric></efac:AwardCriterionParameter></efext:EformsExtension></ext:ExtensionContent></ext:UBLExtension></ext:UBLExtensions><cbc:AwardingCriterionTypeCode listName="award-criterion-type">quality</cbc:AwardingCriterionTypeCode><cbc:Description languageID="FRA">Principe DNSH - Critère d'attribution CA9 - Recyclabilité des bo^tiers, enveloppes et cadres plastiques - Composants internes et éléments de fixation séparables</cbc:Description><cbc:CalculationExpression languageID="FRA">Principe DNSH – Critère d’Attribution CA9 – Recyclabilité des boitiers, enveloppes et cadres plastiques – composants internes et éléments de fixation séparables 

5 points seront attribués si toutes les pièces en matière plastiques &gt; à 25 grammes (des 4 types d’écrans) ne contiennent pas de composants internes ou d’éléments de fixation métalliques moulés, insérés à chaud ou par ultrason, ou collés, à moins que le composant métallique puisse être détaché de la pièces en matière plastique ou qu’il soit séparable à l’aide d’outils d’usage courant. Les rotors de ventilateur sont exclu de cette exigences.

Vérification: le soumissionnaire doit fournir:
1)	De la documentation montrant que le produit ne contient pas de composant internes ou d’éléments de fixation métalliques moulés, insérés à chaud ou par ultrason, ou collés;
2)	Dans le cas où des composants internes ou des éléments de fixation sont moulés, insérés à chaud ou par ultrason, ou collés dans les pièces plastiques, des documents montrant comment ces éléments peuvent être détachés des pièces en matière plastique ou en être séparé à l’aide d’outils d’usage courant
Ou
3)	Si une dérogation est demandée, les conditions d’exemption des exigences légales, techniques ou de sécurité pour un composant interne ou élément de fixation métallique

Les appareils porteurs d’un label écologique de type I satisfaisant aux exigences spécifiées seront réputés conformes  
</cbc:CalculationExpression></cac:SubordinateAwardingCriterion><cac:SubordinateAwardingCriterion><ext:UBLExtensions><ext:UBLExtension><ext:ExtensionContent><efext:EformsExtension><efac:AwardCriterionParameter><efbc:ParameterCode listName="number-weight">poi-exa</efbc:ParameterCode><efbc:ParameterNumeric>5</efbc:ParameterNumeric></efac:AwardCriterionParameter></efext:EformsExtension></ext:ExtensionContent></ext:UBLExtension></ext:UBLExtensions><cbc:AwardingCriterionTypeCode listName="award-criterion-type">quality</cbc:AwardingCriterionTypeCode><cbc:Description languageID="FRA">Principe DNSH - Emballage des écrans 100% recyclable</cbc:Description><cbc:CalculationExpression languageID="FRA">Principe DNSH – Emballage des écrans 100% recyclable

5 points seront attribués si les emballages des 4 types d’écrans, lors de la livraison, sont 100% recyclables (exemple: carton, bois ; contre-exemple: frigolite).

Vérification: Pour chaque modèle d’écran, le soumissionnaire fournit une preuve écrite du fabriquant de l’existence d’un emballage 100% recyclable. 
</cbc:CalculationExpression></cac:SubordinateAwardingCriterion><cac:SubordinateAwardingCriterion><ext:UBLExtensions><ext:UBLExtension><ext:ExtensionContent><efext:EformsExtension><efac:AwardCriterionParameter><efbc:ParameterCode listName="number-weight">poi-exa</efbc:ParameterCode><efbc:ParameterNumeric>5</efbc:ParameterNumeric></efac:AwardCriterionParameter></efext:EformsExtension></ext:ExtensionContent></ext:UBLExtension></ext:UBLExtensions><cbc:AwardingCriterionTypeCode listName="award-criterion-type">quality</cbc:AwardingCriterionTypeCode><cbc:Description languageID="FRA">Principe DNSH - Gestion du produit en fin de vie - Service de collecte, désinfection, réutilisation et recyclage des écrans (ST23)</cbc:Description><cbc:CalculationExpression languageID="FRA">Principe DNSH – Gestion du produit en fin de vie – Service de collecte, désinfection, réutilisation et recyclage des écrans (ST23)

5 points seront accordés si le soumissionnaire fourni (en direct ou via un sous-traitant) un service de réutilisation et de recyclage de l’ensemble des écrans du présent marché ou des composants nécessitant un traitement sélectif conformément à l’annexe VII de la directive DEEE pour les équipements qui ont atteint leur fin de vie. Le service doit inclure les activités suivantes : 
• collecte (système de reprise); 
• traitement confidentiel et effacement sécurisé des données si existantes (sauf si effectués en interne); 
• essai fonctionnel, entretien, réparation et mise à niveau pour préparer les produits à la réutilisation ; 
• re commercialisation des produits en vue de leur réutilisation ; 
• démontage en vue de la réutilisation, du recyclage et/ou de l’élimination des composants. 

Dans le cadre de la fourniture du service, les soumissionnaires doivent déclarer la proportion d’appareils préparés ou recommercialisés en vue de leur réutilisation et de la proportion d’appareils préparés en vue de leur recyclage. 

Les opérations de préparation en vue d’une réutilisation, d’un recyclage et d’une élimination doivent être exécutées en respectant pleinement les exigences énoncées à l’article 8 et aux annexes VII et VIII de la directive 2012/19/UE relative aux DEEE (refonte) et en se référant à la liste des composants pour le traitement sélectif [voir la note explicative ci-dessous]. 

Vérification du ST23 : Le soumissionnaire doit fournir une description des dispositions en matière de collecte, de sécurité des données, de préparation en vue de la réutilisation, de re commercialisation en vue de la réutilisation et du recyclage/de l’élimination. Cela doit inclure, au cours de l’exécution du contrat, la présentation de preuves de la conformité des installations de traitement des DEEE qui seront utilisées.

Note explicative : composants nécessitant un traitement sélectif des DEEE 
Les composants suivants nécessitent un traitement sélectif conformément à l’annexe VII de la directive relative aux DEEE : 
1) les composants contenant du mercure ; 
2) les batteries ; 
3) les cartes de circuit imprimé de plus de 10 cm2 ; 
4) les matières plastiques contenant des retardateurs de flamme bromés ; 
5) les chlorofluorocarbones (CFC), les hydro chlorofluorocarbones (HCFC) ou hydrofluorocarbones (HFC), les hydrocarbures (HC) ; 
6) les câbles électriques extérieurs ; 
7) les condensateurs contenant des polychlorobiphényles (PCB) ; 
8) les composants contenant des fibres céramiques réfractaires ; 
9) les condensateurs électrolytiques contenant des substances dangereuses ; 
10) les équipements contenant des gaz appauvrissant la couche d’ozone ou présentant un potentiel de réchauffement de la planète (PRP) supérieur à 15 ; 
11) les gaz appauvrissant la couche d’ozone, qui doivent être traités conformément au règlement (CE) nº 1005/2009

</cbc:CalculationExpression></cac:SubordinateAwardingCriterion><cac:SubordinateAwardingCriterion><ext:UBLExtensions><ext:UBLExtension><ext:ExtensionContent><efext:EformsExtension><efac:AwardCriterionParameter><efbc:ParameterCode listName="number-weight">poi-exa</efbc:ParameterCode><efbc:ParameterNumeric>5</efbc:ParameterNumeric></efac:AwardCriterionParameter></efext:EformsExtension></ext:ExtensionContent></ext:UBLExtension></ext:UBLExtensions><cbc:AwardingCriterionTypeCode listName="award-criterion-type">quality</cbc:AwardingCriterionTypeCode><cbc:Description languageID="FRA">Prinice DNSH - Gestion du produit en fin de vie - Rapport sur la destination finale des écrans (CEM2)</cbc:Description><cbc:CalculationExpression languageID="FRA">Principe DNSH – Gestion du produit en fin de vie – Rapport sur la destination finale des écrans (CEM2)

Ce critère sera analysé si et seulement si le critère d’attribution n° 7 (principe DNSH - Service de collecte, désinfection, réutilisation et recyclage (ST23)) est rencontré par le soumissionnaire. 

5 points seront accordés si le soumissionnaire est en capacité de fournir un rapport comme décrit ci-après (en ce y compris les moyens de preuves)

Lorsque le soumissionnaire aura collecté en fin de vie les écrans fournis, il présentera un rapport sur l’état des équipements figurant dans les stocks une fois que tous les articles auront été transformés en vue de leur réutilisation, leur recyclage ou leur élimination. Il doit rendre compte de la proportion d’articles réutilisés ou recyclés, et indiquer si ceux-ci sont restés dans l’Union européenne ou ont été exportés
Pour les équipements et composants recyclés dans l’UE, les moyens de preuves suivants pour les installations de traitement doivent être acceptés :
•	Une autorisation délivrée par l’autorité nationale compétente conformément à l’article 23 de la directive 2008/98/CE ; ou
•	Une certification par un tiers du respect des exigences techniques de la norme EN 50625-1 ou d’un régime de conformité équivalent.
Lorsque les équipements et composants sont exportés en vue d’une réutilisation ou d’un recyclage, les contractants doivent communiquer les informations suivantes concernant le transfert et le traitement :
•	Les informations relatives au transfert des équipements destinés à être réutilisés, conformément à l’annexe VI de la directive 2012/19/UE relative aux DEEE
Les DEEE exportées afin d’être traitées en dehors de l’Union nécessitent une certification par un tier du respect des exigences minimales applicables aux DEEE définies dans le critère, des exigences techniques de la norme EN 50625-1 ou d’un régime de conformité équivalent.
Vérification du CEM2 : le soumissionnaire signera une déclaration sur l’honneur qu’il est en capacité de transmettre le rapport comme décrit ci-avant (en ce y compris les moyens de preuves).
</cbc:CalculationExpression></cac:SubordinateAwardingCriterion></cac:AwardingCriterion></cac:AwardingTerms><cac:AdditionalInformationParty><cac:PartyIdentification><cbc:ID schemeName="organization">ORG-0001</cbc:ID></cac:PartyIdentification></cac:AdditionalInformationParty><cac:TenderRecipientParty><cbc:EndpointID>https://www.publicprocurement.be</cbc:EndpointID><cac:PartyIdentification><cbc:ID schemeName="organization">ORG-0001</cbc:ID></cac:PartyIdentification></cac:TenderRecipientParty><cac:TenderValidityPeriod><cbc:DurationMeasure unitCode="DAY">120</cbc:DurationMeasure></cac:TenderValidityPeriod><cac:AppealTerms><cac:PresentationPeriod><cbc:Description languageID="FRA">S'en référer au Tribunal de Première Instance de l'Arrondissement de Charleroi</cbc:Description></cac:PresentationPeriod><cac:AppealReceiverParty><cac:PartyIdentification><cbc:ID schemeName="organization">ORG-0002</cbc:ID></cac:PartyIdentification></cac:AppealReceiverParty><cac:MediationParty><cac:PartyIdentification><cbc:ID schemeName="organization">ORG-0002</cbc:ID></cac:PartyIdentification></cac:MediationParty></cac:AppealTerms><cac:Language><cbc:ID>FRA</cbc:ID></cac:Language><cac:PostAwardProcess><cbc:ElectronicOrderUsageIndicator>false</cbc:ElectronicOrderUsageIndicator><cbc:ElectronicPaymentUsageIndicator>false</cbc:ElectronicPaymentUsageIndicator></cac:PostAwardProcess></cac:TenderingTerms><cac:TenderingProcess><cbc:SubmissionMethodCode listName="esubmission">required</cbc:SubmissionMethodCode><cbc:GovernmentAgreementConstraintIndicator>false</cbc:GovernmentAgreementConstraintIndicator><cac:TenderSubmissionDeadlinePeriod><cbc:EndDate>2025-07-07+02:00</cbc:EndDate><cbc:EndTime>10:30:00+02:00</cbc:EndTime></cac:TenderSubmissionDeadlinePeriod><cac:OpenTenderEvent><cbc:OccurrenceDate>2025-07-07+02:00</cbc:OccurrenceDate><cbc:OccurrenceTime>10:30:00+02:00</cbc:OccurrenceTime><cac:OccurenceLocation><cbc:Description languageID="FRA">aptaskil asbl, Zoning Industriel de Seneffe - Zone C, rue Charles Richet à 7180 Seneffe</cbc:Description></cac:OccurenceLocation></cac:OpenTenderEvent><cac:AuctionTerms><cbc:AuctionConstraintIndicator>false</cbc:AuctionConstraintIndicator></cac:AuctionTerms><cac:FrameworkAgreement><cbc:MaximumOperatorQuantity>1</cbc:MaximumOperatorQuantity></cac:FrameworkAgreement><cac:ContractingSystem><cbc:ContractingSystemTypeCode listName="dps-usage">none</cbc:ContractingSystemTypeCode></cac:ContractingSystem><cac:ContractingSystem><cbc:ContractingSystemTypeCode listName="framework-agreement">fa-wo-rc</cbc:ContractingSystemTypeCode></cac:ContractingSystem></cac:TenderingProcess><cac:ProcurementProject><cbc:ID schemeName="InternalID">IL/CG/PNRR/2024/011 1_1</cbc:ID><cbc:Name languageID="FRA">MARCHÉ DE FOURNITURES - ACHAT D'ÉQUIPEMENTS POUR UNE COMMUNICATION ET UNE SIGNALÉTIQUE DIGITALE (estampillé DNSH)</cbc:Name><cbc:Description languageID="FRA">aptaskil asbl est un centre de compétences qui forme aux métiers de la chimie, de la biopharmacie et des biotechnologies. Nous formons 3 types de publics : des personnes travaillant dans les entreprises chimiques et pharmaceutiques, des enseignants et des étudiants, des chercheurs d’emploi. 

Pour répondre à la forte croissance du secteur, nous agrandissons notre centre et disposons de nouvelles salles de cours, et de nouvelles zones d’apprentissage pratique réparties sur deux sites, à Seneffe (4.000 m2) et à Liège (800 m2). Nous souhaitons équiper ces lieux d’un dispositif de communication et de signalétique digitale.

Principe DNSH : Cet investissement est subventionné par l’Europe et la Région wallonne (Plan National de Relance et de Résilience et Plan de Relance de la Wallonie). Il en découle que le présent marché public intègre le respect du principe DNSH et les résultats de l’analyse ex hante spécifiques aux équipements numériques notifiés dans l’accord de subvention. Dans ce cadre, des clauses contractuelles, des exigences techniques et des critères d’attribution spécifiques au principe DNSH ont été intégrées au présent marché. Des informations complémentaires pour aider à la compréhension du principe DNSH sont intégrées au point I.14 Financement/principes DNSH

Objet social du marché : du fait de son activité de dispense de formations, le Centre de compétence aptaskil assure une mission sociale en participant à l’insertion professionnelle des futurs travailleurs (chercheurs d’emploi et des étudiants) et au maintien de l’employabilité des travailleurs en activité. Le présent marché permettra de soutenir cette mission sociale en permettant aux apprenants d’évoluer dans un environnement digital. Le soumissionnaire, par son activité de livraison et d’installation d’équipements, participera donc au renforcement de la mission sociale d’aptaskil.   </cbc:Description><cbc:ProcurementTypeCode listName="contract-nature">supplies</cbc:ProcurementTypeCode><cac:MainCommodityClassification><cbc:ItemClassificationCode listName="cpv">32000000</cbc:ItemClassificationCode></cac:MainCommodityClassification><cac:RealizedLocation><cbc:Description languageID="FRA">aptaskil asbl</cbc:Description><cac:Address><cbc:StreetName>Zoning Industriel de Seneffe - Zone C</cbc:StreetName><cbc:CityName>Seneffe</cbc:CityName><cbc:PostalZone>7180</cbc:PostalZone><cbc:CountrySubentityCode listName="nuts">BE32B</cbc:CountrySubentityCode><cac:Country><cbc:IdentificationCode listName="country">BEL</cbc:IdentificationCode></cac:Country></cac:Address></cac:RealizedLocation><cac:RealizedLocation><cbc:Description languageID="FRA">aptaskil - Site de Liège</cbc:Description><cac:Address><cbc:StreetName>LEGIAPARK Rue Louise Michel</cbc:StreetName><cbc:CityName>Liège</cbc:CityName><cbc:PostalZone>4000</cbc:PostalZone><cbc:CountrySubentityCode listName="nuts">BE331</cbc:CountrySubentityCode><cac:Country><cbc:IdentificationCode listName="country">BEL</cbc:IdentificationCode></cac:Country></cac:Address></cac:RealizedLocation><cac:RealizedLocation><cbc:Description languageID="FRA">aptaskil - Site de Liège</cbc:Description><cac:Address><cbc:StreetName>LEGIAPARK Rue Louise Michel</cbc:StreetName><cbc:CityName>Liège</cbc:CityName><cbc:PostalZone>4000</cbc:PostalZone><cbc:CountrySubentityCode listName="nuts">BE332</cbc:CountrySubentityCode><cac:Country><cbc:IdentificationCode listName="country">BEL</cbc:IdentificationCode></cac:Country></cac:Address></cac:RealizedLocation><cac:RealizedLocation><cbc:Description languageID="FRA">aptaskil - Site de Liège</cbc:Description><cac:Address><cbc:StreetName>LEGIAPARK Rue Louise Michel</cbc:StreetName><cbc:CityName>Liège</cbc:CityName><cbc:PostalZone>4000</cbc:PostalZone><cbc:CountrySubentityCode listName="nuts">BE335</cbc:CountrySubentityCode><cac:Country><cbc:IdentificationCode listName="country">BEL</cbc:IdentificationCode></cac:Country></cac:Address></cac:RealizedLocation><cac:RealizedLocation><cbc:Description languageID="FRA">aptaskil - Site de Liège</cbc:Description><cac:Address><cbc:StreetName>LEGIAPARK Rue Louise Michel</cbc:StreetName><cbc:CityName>Liège</cbc:CityName><cbc:PostalZone>4000</cbc:PostalZone><cbc:CountrySubentityCode listName="nuts">BE334</cbc:CountrySubentityCode><cac:Country><cbc:IdentificationCode listName="country">BEL</cbc:IdentificationCode></cac:Country></cac:Address></cac:RealizedLocation><cac:RealizedLocation><cbc:Description languageID="FRA">aptaskil - Site de Liège</cbc:Description><cac:Address><cbc:StreetName>LEGIAPARK Rue Louise Michel</cbc:StreetName><cbc:CityName>Liège</cbc:CityName><cbc:PostalZone>4000</cbc:PostalZone><cbc:CountrySubentityCode listName="nuts">BE336</cbc:CountrySubentityCode><cac:Country><cbc:IdentificationCode listName="country">BEL</cbc:IdentificationCode></cac:Country></cac:Address></cac:RealizedLocation><cac:PlannedPeriod><cbc:DurationMeasure unitCode="MONTH">12</cbc:DurationMeasure></cac:PlannedPeriod></cac:ProcurementProject></cac:ProcurementProjectLot></ContractNotice>