<?xml version="1.0" encoding="UTF-8" standalone="yes"?><ContractNotice xmlns:ext="urn:oasis:names:specification:ubl:schema:xsd:CommonExtensionComponents-2" xmlns="urn:oasis:names:specification:ubl:schema:xsd:ContractNotice-2" xmlns:ns7="urn:oasis:names:specification:ubl:schema:xsd:ContractAwardNotice-2" xmlns:cac="urn:oasis:names:specification:ubl:schema:xsd:CommonAggregateComponents-2" xmlns:cbc="urn:oasis:names:specification:ubl:schema:xsd:CommonBasicComponents-2" xmlns:ns9="urn:oasis:names:specification:ubl:schema:xsd:PriorInformationNotice-2" xmlns:efac="http://data.europa.eu/p27/eforms-ubl-extension-aggregate-components/1" xmlns:efbc="http://data.europa.eu/p27/eforms-ubl-extension-basic-components/1" xmlns:efext="http://data.europa.eu/p27/eforms-ubl-extensions/1"><ext:UBLExtensions><ext:UBLExtension><ext:ExtensionContent><efext:EformsExtension><efbc:TransmissionDate>2025-06-10+02:00</efbc:TransmissionDate><efbc:TransmissionTime>00:00:00+02:00</efbc:TransmissionTime><efac:NoticeSubType><cbc:SubTypeCode listName="notice-subtype">E3</cbc:SubTypeCode></efac:NoticeSubType><efac:Organizations><efac:Organization><efac:Company><cbc:WebsiteURI>http://www.aquafin.be</cbc:WebsiteURI><cac:PartyIdentification><cbc:ID schemeName="organization">ORG-0001</cbc:ID></cac:PartyIdentification><cac:PartyName><cbc:Name languageID="NLD">Aquafin NV</cbc:Name></cac:PartyName><cac:PostalAddress><cbc:StreetName>Dijkstraat 8</cbc:StreetName><cbc:Department>Aquafin NV - Directie Projectmanagement</cbc:Department><cbc:CityName>Aartselaar</cbc:CityName><cbc:PostalZone>2630</cbc:PostalZone><cbc:CountrySubentityCode listName="nuts">BE211</cbc:CountrySubentityCode><cac:Country><cbc:IdentificationCode listName="country">BEL</cbc:IdentificationCode></cac:Country></cac:PostalAddress><cac:PartyLegalEntity><cbc:CompanyID>0440691388_4618</cbc:CompanyID></cac:PartyLegalEntity><cac:Contact><cbc:Telephone>+32 34504511</cbc:Telephone><cbc:ElectronicMail>aanbestedingen@aquafin.be</cbc:ElectronicMail></cac:Contact></efac:Company></efac:Organization><efac:Organization><efac:Company><cbc:WebsiteURI>https://bosa.belgium.be</cbc:WebsiteURI><cac:PartyIdentification><cbc:ID schemeName="organization">ORG-0002</cbc:ID></cac:PartyIdentification><cac:PartyName><cbc:Name languageID="NLD">FOD Beleid en Ondersteuning</cbc:Name></cac:PartyName><cac:PostalAddress><cbc:StreetName>Simon Bolivarlaan 30, bus 1</cbc:StreetName><cbc:CityName>Brussel</cbc:CityName><cbc:PostalZone>1000</cbc:PostalZone><cbc:CountrySubentityCode listName="nuts">BE100</cbc:CountrySubentityCode><cac:Country><cbc:IdentificationCode listName="country">BEL</cbc:IdentificationCode></cac:Country></cac:PostalAddress><cac:PartyLegalEntity><cbc:CompanyID>BE001</cbc:CompanyID></cac:PartyLegalEntity><cac:Contact><cbc:Telephone>+32 2 740 80 00</cbc:Telephone><cbc:ElectronicMail>revise@publicprocurement.be</cbc:ElectronicMail></cac:Contact></efac:Company></efac:Organization><efac:Organization><efac:Company><cac:PartyIdentification><cbc:ID schemeName="organization">ORG-0003</cbc:ID></cac:PartyIdentification><cac:PartyName><cbc:Name languageID="NLD">Bevoegde Rechtbank te Antwerpen</cbc:Name></cac:PartyName><cac:PostalAddress><cbc:CityName>Antwerpen</cbc:CityName><cbc:PostalZone>2000</cbc:PostalZone><cbc:CountrySubentityCode listName="nuts">BE211</cbc:CountrySubentityCode><cac:Country><cbc:IdentificationCode listName="country">BEL</cbc:IdentificationCode></cac:Country></cac:PostalAddress><cac:PartyLegalEntity><cbc:CompanyID>000000000</cbc:CompanyID></cac:PartyLegalEntity></efac:Company></efac:Organization></efac:Organizations></efext:EformsExtension></ext:ExtensionContent></ext:UBLExtension></ext:UBLExtensions><cbc:UBLVersionID>2.3</cbc:UBLVersionID><cbc:CustomizationID>eforms-sdk-1.13</cbc:CustomizationID><cbc:ID schemeName="notice-id">57638b42-0360-4df9-b7c4-4975319ccc1f</cbc:ID><cbc:ContractFolderID>44fd2d13-1066-4fa1-ab4a-19f8cfd70de7</cbc:ContractFolderID><cbc:IssueDate>2025-06-10+02:00</cbc:IssueDate><cbc:IssueTime>00:00:00+02:00</cbc:IssueTime><cbc:VersionID>01</cbc:VersionID><cbc:RegulatoryDomain>32014L0024</cbc:RegulatoryDomain><cbc:NoticeTypeCode listName="competition">cn-standard</cbc:NoticeTypeCode><cbc:NoticeLanguageCode listName="language">NLD</cbc:NoticeLanguageCode><cac:ContractingParty><cbc:BuyerProfileURI>https://www.publicprocurement.be/bda?organisationIds=4618&amp;includeOrganisationChildren=true</cbc:BuyerProfileURI><cac:ContractingPartyType><cbc:PartyTypeCode listName="buyer-legal-type">body-pl</cbc:PartyTypeCode></cac:ContractingPartyType><cac:ContractingPartyType><cbc:PartyTypeCode listName="buyer-contracting-type">not-cont-ent</cbc:PartyTypeCode></cac:ContractingPartyType><cac:ContractingActivity><cbc:ActivityTypeCode listName="authority-activity">env-pro</cbc:ActivityTypeCode></cac:ContractingActivity><cac:Party><cac:PartyIdentification><cbc:ID schemeName="organization">ORG-0001</cbc:ID></cac:PartyIdentification><cac:ServiceProviderParty><cbc:ServiceTypeCode listName="organisation-role">ted-esen</cbc:ServiceTypeCode><cac:Party><cac:PartyIdentification><cbc:ID schemeName="organization">ORG-0002</cbc:ID></cac:PartyIdentification></cac:Party></cac:ServiceProviderParty></cac:Party></cac:ContractingParty><cac:TenderingTerms><cac:TendererQualificationRequest><cac:SpecificTendererRequirement><cbc:TendererRequirementTypeCode listName="exclusion-grounds-source">epo-notice</cbc:TendererRequirementTypeCode></cac:SpecificTendererRequirement></cac:TendererQualificationRequest><cac:TendererQualificationRequest><cac:SpecificTendererRequirement><cbc:TendererRequirementTypeCode listName="exclusion-ground">exg-natl</cbc:TendererRequirementTypeCode></cac:SpecificTendererRequirement></cac:TendererQualificationRequest></cac:TenderingTerms><cac:TenderingProcess><cbc:Description languageID="NLD">Voor deze opdracht wordt de nationale regelgeving van volgende procedure toegepast: vereenvoudigde onderhandelingsprocedure met voorafgaande bekendmaking</cbc:Description><cbc:ProcedureCode listName="procurement-procedure-type">oth-single</cbc:ProcedureCode></cac:TenderingProcess><cac:ProcurementProject><cbc:ID schemeName="InternalID">V1511002</cbc:ID><cbc:Name languageID="NLD">V1511002 -  Paal-Beringen, vervangen laagspanning en leidingwerk, PS Katermeerstraat</cbc:Name><cbc:Description languageID="NLD">V1511002 -  Paal-Beringen, vervangen laagspanning en leidingwerk, PS Katermeerstraat. PS Katermeerstraat te Beringen was in 1993 een 3+1 opstelling met 35 liter/sec (126m³/u) per pomp. Het PS is in 2009 aangepast naar 1+1 opstelling.  Huidige opstelling is een 1+1 opstelling met 230m³/u werkpunt per pomp met een natte en droge kelder. Nat opgestelde dompelpompen. Pompstation is niet omheind. Ligging pompstation op de hoek van N29 Paalsesteenweg en Katermeerstraat.  Verschillende onderdelen zoals ALSB, persleidingen, appendages, pompen, … hebben hun technische levensduur bereikt en daarom wordt er naar een algemene renovatie gekeken volgens de huidige standaarden van een pompstation.  Het pompstation dient grondig gerenoveerd te worden: • Bouwkundige werken zoals betonzaagwerken t.b.v. aanpassingen aan toegangsopeningen dekplaat, nieuwe muurdoorvoeren plaatsen, … • Elektrische werken zoals het plaatsen van een volledig nieuw ALSB, nieuwe bekabeling, nieuwe instrumentatie aansluiten, … • Elektromechanische werken zoals het plaatsen/ aansluiten van pompen, het leveren/ plaatsen &amp; aansluiten van instrumentatie, leveren en plaatsen van appendages, … </cbc:Description><cbc:ProcurementTypeCode listName="contract-nature">works</cbc:ProcurementTypeCode><cac:MainCommodityClassification><cbc:ItemClassificationCode listName="cpv">45252130</cbc:ItemClassificationCode></cac:MainCommodityClassification><cac:AdditionalCommodityClassification><cbc:ItemClassificationCode listName="cpv">39350000</cbc:ItemClassificationCode></cac:AdditionalCommodityClassification><cac:RealizedLocation><cac:Address><cbc:CityName>Paal-Beringen</cbc:CityName><cbc:CountrySubentityCode listName="nuts">BE224</cbc:CountrySubentityCode><cac:Country><cbc:IdentificationCode listName="country">BEL</cbc:IdentificationCode></cac:Country></cac:Address></cac:RealizedLocation></cac:ProcurementProject><cac:ProcurementProjectLot><cbc:ID schemeName="Lot">LOT-0001</cbc:ID><cac:TenderingTerms><cbc:FundingProgramCode listName="eu-funded">no-eu-funds</cbc:FundingProgramCode><cac:CallForTendersDocumentReference><cbc:ID>TenderDocumentRef-LOT-0001</cbc:ID><cbc:DocumentType>non-restricted-document</cbc:DocumentType><cac:Attachment><cac:ExternalReference><cbc:URI>https://www.publicprocurement.be/publication-workspaces/34616df3-c4cf-4dd0-b561-7f67ec18b1f7/documents</cbc:URI></cac:ExternalReference></cac:Attachment></cac:CallForTendersDocumentReference><cac:TendererQualificationRequest><cac:SpecificTendererRequirement><cbc:TendererRequirementTypeCode listName="selection-criteria-source">epo-procurement-document</cbc:TendererRequirementTypeCode></cac:SpecificTendererRequirement></cac:TendererQualificationRequest><cac:TendererQualificationRequest><cac:SpecificTendererRequirement><cbc:TendererRequirementTypeCode listName="reserved-procurement">none</cbc:TendererRequirementTypeCode></cac:SpecificTendererRequirement></cac:TendererQualificationRequest><cac:ContractExecutionRequirement><cbc:ExecutionRequirementCode listName="reserved-execution">no</cbc:ExecutionRequirementCode></cac:ContractExecutionRequirement><cac:ContractExecutionRequirement><cbc:ExecutionRequirementCode listName="ecatalog-submission">not-allowed</cbc:ExecutionRequirementCode></cac:ContractExecutionRequirement><cac:ContractExecutionRequirement><cbc:ExecutionRequirementCode listName="esignature-submission">true</cbc:ExecutionRequirementCode></cac:ContractExecutionRequirement><cac:AwardingTerms><cac:AwardingCriterion><cac:SubordinateAwardingCriterion><cbc:AwardingCriterionTypeCode listName="award-criterion-type">price</cbc:AwardingCriterionTypeCode><cbc:Description languageID="NLD">prijs</cbc:Description></cac:SubordinateAwardingCriterion></cac:AwardingCriterion></cac:AwardingTerms><cac:TenderRecipientParty><cbc:EndpointID>https://www.publicprocurement.be/supplier/enterprises/0/tendering-workspaces/publication-workspace-detail/34616df3-c4cf-4dd0-b561-7f67ec18b1f7/general</cbc:EndpointID></cac:TenderRecipientParty><cac:AppealTerms><cac:AppealReceiverParty><cac:PartyIdentification><cbc:ID schemeName="organization">ORG-0003</cbc:ID></cac:PartyIdentification></cac:AppealReceiverParty></cac:AppealTerms><cac:Language><cbc:ID>NLD</cbc:ID></cac:Language><cac:PostAwardProcess><cbc:ElectronicOrderUsageIndicator>false</cbc:ElectronicOrderUsageIndicator><cbc:ElectronicPaymentUsageIndicator>false</cbc:ElectronicPaymentUsageIndicator></cac:PostAwardProcess></cac:TenderingTerms><cac:TenderingProcess><cbc:SubmissionMethodCode listName="esubmission">required</cbc:SubmissionMethodCode><cac:TenderSubmissionDeadlinePeriod><cbc:EndDate>2025-08-26+02:00</cbc:EndDate><cbc:EndTime>11:10:00+02:00</cbc:EndTime></cac:TenderSubmissionDeadlinePeriod><cac:AuctionTerms><cbc:AuctionConstraintIndicator>false</cbc:AuctionConstraintIndicator></cac:AuctionTerms><cac:FrameworkAgreement><cac:SubsequentProcessTenderRequirement><cbc:Name>buyer-categories</cbc:Name></cac:SubsequentProcessTenderRequirement></cac:FrameworkAgreement><cac:ContractingSystem><cbc:ContractingSystemTypeCode listName="framework-agreement">none</cbc:ContractingSystemTypeCode></cac:ContractingSystem><cac:ContractingSystem><cbc:ContractingSystemTypeCode listName="dps-usage">none</cbc:ContractingSystemTypeCode></cac:ContractingSystem></cac:TenderingProcess><cac:ProcurementProject><cbc:ID schemeName="InternalID">1</cbc:ID><cbc:Name languageID="NLD">V1511002 - 1</cbc:Name><cbc:Description languageID="NLD">V1511002 -  Paal-Beringen, vervangen laagspanning en leidingwerk, PS Katermeerstraat. PS Katermeerstraat te Beringen was in 1993 een 3+1 opstelling met 35 liter/sec (126m³/u) per pomp. Het PS is in 2009 aangepast naar 1+1 opstelling.  Huidige opstelling is een 1+1 opstelling met 230m³/u werkpunt per pomp met een natte en droge kelder. Nat opgestelde dompelpompen. Pompstation is niet omheind. Ligging pompstation op de hoek van N29 Paalsesteenweg en Katermeerstraat.  Verschillende onderdelen zoals ALSB, persleidingen, appendages, pompen, … hebben hun technische levensduur bereikt en daarom wordt er naar een algemene renovatie gekeken volgens de huidige standaarden van een pompstation.  Het pompstation dient grondig gerenoveerd te worden: • Bouwkundige werken zoals betonzaagwerken t.b.v. aanpassingen aan toegangsopeningen dekplaat, nieuwe muurdoorvoeren plaatsen, … • Elektrische werken zoals het plaatsen van een volledig nieuw ALSB, nieuwe bekabeling, nieuwe instrumentatie aansluiten, … • Elektromechanische werken zoals het plaatsen/ aansluiten van pompen, het leveren/ plaatsen &amp; aansluiten van instrumentatie, leveren en plaatsen van appendages, …</cbc:Description><cbc:ProcurementTypeCode listName="contract-nature">works</cbc:ProcurementTypeCode><cbc:Note languageID="NLD">Uitvoeringstermijn :
De uitvoeringstermijn van de opdracht bedraagt 300 kalenderdagen, opgesplitst in deelfasen:
• 60 kalenderdagen voor indienen technische voorstellen.
• 30 kalenderdagen nazicht technische voorstellen.
• 180 kalenderdagen voor de uitvoeringsfase werken.
o 135 kalenderdagen voor de fabricage van alle materialen.
o 45 kalenderdagen voor de montage tot een werkingsklaar geheel.
• 30 kalenderdagen voor de proefperiode  

Plaatsbezoek :
Gezien met de aard van de locatie een aantal specifieke moeilijkheden gepaard gaan, wordt de aannemer verplicht vóór zijn prijsopmaak de plaats der werken te bezichtigen. Dit plaatsbezoek wordt éénmalig georganiseerd op afspraak. De aanwezigheid dient te worden bevestigd aan Karel Palmers, projectverantwoordelijke, karel.palmers@aquafin.be, +32 (0) 474 542 591. </cbc:Note><cac:MainCommodityClassification><cbc:ItemClassificationCode listName="cpv">45252130</cbc:ItemClassificationCode></cac:MainCommodityClassification><cac:AdditionalCommodityClassification><cbc:ItemClassificationCode listName="cpv">45252130</cbc:ItemClassificationCode></cac:AdditionalCommodityClassification><cac:RealizedLocation><cac:Address><cbc:CityName>Paal-Beringen</cbc:CityName><cbc:CountrySubentityCode listName="nuts">BE224</cbc:CountrySubentityCode><cac:Country><cbc:IdentificationCode listName="country">BEL</cbc:IdentificationCode></cac:Country></cac:Address></cac:RealizedLocation><cac:PlannedPeriod><cbc:DurationMeasure unitCode="DAY">300</cbc:DurationMeasure></cac:PlannedPeriod></cac:ProcurementProject></cac:ProcurementProjectLot></ContractNotice>